<annotation>
	<folder>Husky</folder>
	<filename>277.jpg</filename>
	<path>C:\Users\crist\Downloads\Husky\277.jpg</path>
	<source>
		<database>Unknown</database>
	</source>
	<size>
		<width>626</width>
		<height>414</height>
		<depth>3</depth>
	</size>
	<segmented>0</segmented>
	<object>
		<name>husky</name>
		<pose>Unspecified</pose>
		<truncated>0</truncated>
		<difficult>0</difficult>
		<bndbox>
			<xmin>252</xmin>
			<ymin>27</ymin>
			<xmax>575</xmax>
			<ymax>412</ymax>
		</bndbox>
	</object>
</annotation>
